<?xml version="1.0" encoding="UTF-8"?>
<objects serializationModel="Studio.02.02.00">
	<object class="Workspace" id="{88f994a2-4fba-420c-a423-1b67250c9936}">
		<relationship name="masterEventFolder">
			<destination>{e8ac17a7-ea6e-42e6-b158-337f5e7a0c97}</destination>
		</relationship>
		<relationship name="masterTagFolder">
			<destination>{0ef443b3-56d2-4d0b-a0d8-6dd7cf09c8fa}</destination>
		</relationship>
		<relationship name="masterEffectPresetFolder">
			<destination>{b54e500a-0865-4d72-bfef-a9911dd39664}</destination>
		</relationship>
		<relationship name="masterParameterPresetFolder">
			<destination>{364e7bf1-495f-4201-b74f-e00de567f821}</destination>
		</relationship>
		<relationship name="masterBankFolder">
			<destination>{4ff812de-fb8b-4bd6-ae5d-aa1c5eee8605}</destination>
		</relationship>
		<relationship name="masterSandboxFolder">
			<destination>{d4a2e71a-92f0-4b2d-9071-67622fc51d4f}</destination>
		</relationship>
		<relationship name="masterAssetFolder">
			<destination>{70d50490-851e-41a2-b858-5d3587e48b17}</destination>
		</relationship>
		<relationship name="mixer">
			<destination>{8b516656-b86f-4822-a3d7-afd47e6c2632}</destination>
		</relationship>
		<relationship name="profilerSessionFolder">
			<destination>{bbd49c95-74b8-4653-9d9c-92931c506d46}</destination>
		</relationship>
		<relationship name="platforms">
			<destination>{dbb99b04-50b3-4b47-bbe8-8b869e131ad6}</destination>
		</relationship>
	</object>
</objects>
